stellargraph/__init__.py
stellargraph/calibration.py
stellargraph/ensemble.py
stellargraph/globalvar.py
stellargraph/losses.py
stellargraph/random.py
stellargraph/version.py
stellargraph/connector/__init__.py
stellargraph/connector/neo4j/__init__.py
stellargraph/connector/neo4j/graph.py
stellargraph/connector/neo4j/mapper.py
stellargraph/connector/neo4j/sampler.py
stellargraph/core/__init__.py
stellargraph/core/convert.py
stellargraph/core/element_data.py
stellargraph/core/experimental.py
stellargraph/core/graph.py
stellargraph/core/indexed_array.py
stellargraph/core/numpy_elements.py
stellargraph/core/schema.py
stellargraph/core/utils.py
stellargraph/core/validation.py
stellargraph/data/__init__.py
stellargraph/data/converter.py
stellargraph/data/edge_splitter.py
stellargraph/data/epgm.py
stellargraph/data/explorer.py
stellargraph/data/loader.py
stellargraph/data/node_splitter.py
stellargraph/data/unsupervised_sampler.py
stellargraph/datasets/__init__.py
stellargraph/datasets/dataset_loader.py
stellargraph/datasets/datasets.py
stellargraph/interpretability/__init__.py
stellargraph/interpretability/saliency_maps/__init__.py
stellargraph/interpretability/saliency_maps/integrated_gradients.py
stellargraph/interpretability/saliency_maps/integrated_gradients_gat.py
stellargraph/interpretability/saliency_maps/saliency_gat.py
stellargraph/layer/__init__.py
stellargraph/layer/appnp.py
stellargraph/layer/attri2vec.py
stellargraph/layer/cluster_gcn.py
stellargraph/layer/deep_graph_infomax.py
stellargraph/layer/gcn.py
stellargraph/layer/gcn_lstm.py
stellargraph/layer/graph_attention.py
stellargraph/layer/graph_classification.py
stellargraph/layer/graphsage.py
stellargraph/layer/hinsage.py
stellargraph/layer/knowledge_graph.py
stellargraph/layer/link_inference.py
stellargraph/layer/misc.py
stellargraph/layer/node2vec.py
stellargraph/layer/ppnp.py
stellargraph/layer/preprocessing_layer.py
stellargraph/layer/rgcn.py
stellargraph/layer/sort_pooling.py
stellargraph-1.2.1.dist-info/AUTHORS
stellargraph-1.2.1.dist-info/LICENSE
stellargraph-1.2.1.dist-info/METADATA
stellargraph-1.2.1.dist-info/WHEEL
stellargraph-1.2.1.dist-info/top_level.txt
stellargraph-1.2.1.dist-info/RECORD
