Metadata-Version: 2.1
Name: stellargraph
Version: 1.2.1
Summary: Python library for machine learning on graphs
Home-page: https://github.com/stellargraph/stellargraph
Author: Data61, CSIRO
Author-email: stellar.admin@csiro.au
License: Apache 2.0
Platform: UNKNOWN
Classifier: Programming Language :: Python :: 3
Classifier: Operating System :: OS Independent
Classifier: Development Status :: 3 - Alpha
Classifier: Intended Audience :: Science/Research
Classifier: License :: OSI Approved :: Apache Software License
Classifier: Topic :: Scientific/Engineering :: Artificial Intelligence
Requires-Python: >=3.6.0, <3.9.0
Provides-Extra: demos
Provides-Extra: igraph
Provides-Extra: neo4j
Provides-Extra: test
